pointset/__init__.py
pointset/pointset.py
pointset-0.1.9.dist-info/licenses/LICENSE
pointset-0.1.9.dist-info/METADATA
pointset-0.1.9.dist-info/WHEEL
pointset-0.1.9.dist-info/top_level.txt
pointset-0.1.9.dist-info/RECORD
