Metadata-Version: 2.4
Name: pointset
Version: 0.1.9
Summary: Simple EPSG transformations using PyProj
Requires-Python: >=3.8
License-File: LICENSE
Requires-Dist: numpy>=1.24.4
Requires-Dist: pyproj>=3.5.0
Dynamic: license-file
